onnxruntime/__init__.py
onnxruntime/ThirdPartyNotices.txt
onnxruntime/Privacy.md
onnxruntime/LICENSE
onnxruntime/transformers/onnx_model_gpt2.py
onnxruntime/transformers/float16.py
onnxruntime/transformers/bert_test_data.py
onnxruntime/transformers/onnx_model_bert_keras.py
onnxruntime/transformers/fusion_conformer_attention.py
onnxruntime/transformers/shape_infer_helper.py
onnxruntime/transformers/fusion_transpose.py
onnxruntime/transformers/fusion_embedlayer.py
onnxruntime/transformers/onnx_model_bert.py
onnxruntime/transformers/fusion_reshape.py
onnxruntime/transformers/onnx_model_phi.py
onnxruntime/transformers/fusion_biassplitgelu.py
onnxruntime/transformers/fusion_skip_group_norm.py
onnxruntime/transformers/fusion_attention_vae.py
onnxruntime/transformers/fusion_gpt_attention.py
onnxruntime/transformers/fusion_bias_add.py
onnxruntime/transformers/__init__.py
onnxruntime/transformers/fusion_biasgelu.py
onnxruntime/transformers/bert_perf_test.py
onnxruntime/transformers/fusion_gelu.py
onnxruntime/transformers/fusion_skiplayernorm.py
onnxruntime/transformers/onnx_model_unet.py
onnxruntime/transformers/fusion_nhwc_conv.py
onnxruntime/transformers/fusion_qordered_gelu.py
onnxruntime/transformers/affinity_helper.py
onnxruntime/transformers/dynamo_onnx_helper.py
onnxruntime/transformers/huggingface_models.py
onnxruntime/transformers/convert_tf_models_to_pytorch.py
onnxruntime/transformers/convert_generation.py
onnxruntime/transformers/quantize_helper.py
onnxruntime/transformers/fusion_group_norm.py
onnxruntime/transformers/machine_info.py
onnxruntime/transformers/fusion_simplified_layernorm.py
onnxruntime/transformers/fusion_gpt_attention_no_past.py
onnxruntime/transformers/fusion_rotary_attention.py
onnxruntime/transformers/fusion_attention_unet.py
onnxruntime/transformers/onnx_model.py
onnxruntime/transformers/metrics.py
onnxruntime/transformers/fusion_layernorm.py
onnxruntime/transformers/large_model_exporter.py
onnxruntime_training-1.19.2.dist-info/entry_points.txt
onnxruntime_training-1.19.2.dist-info/WHEEL
onnxruntime_training-1.19.2.dist-info/RECORD
onnxruntime_training-1.19.2.dist-info/top_level.txt
onnxruntime_training-1.19.2.dist-info/METADATA
